sqlalchemy_session_proxy/__init__.py
sqlalchemy_session_proxy/session_proxy.py
sqlalchemy_session_proxy-0.3.0.dist-info/METADATA
sqlalchemy_session_proxy-0.3.0.dist-info/WHEEL
sqlalchemy_session_proxy-0.3.0.dist-info/top_level.txt
sqlalchemy_session_proxy-0.3.0.dist-info/RECORD
