Metadata-Version: 2.4
Name: sqlalchemy-session-proxy
Version: 0.3.0
Summary: A lightweight proxy for SQLAlchemy sessions that seamlessly supports both synchronous (`Session`) and asynchronous (`AsyncSession`) usage. This library provides a unified interface to interact with SQLAlchemy sessions, making it easy to write code that works in both sync and async environments.
Author-email: Tercel <tercel.yi@gmail.com>
License: Apache-2.0
Project-URL: Homepage, https://github.com/aipartnerup/sqlalchemy-session-proxy
Project-URL: Source, https://github.com/aipartnerup/sqlalchemy-session-proxy
Keywords: sqlalchemy,database session proxy
Classifier: Development Status :: 4 - Beta
Classifier: Intended Audience :: Developers
Classifier: License :: OSI Approved :: Apache Software License
Classifier: Programming Language :: Python :: 3
Classifier: Programming Language :: Python :: 3.10
Classifier: Programming Language :: Python :: 3.11
Classifier: Programming Language :: Python :: 3.12
Requires-Python: >=3.10
Requires-Dist: sqlalchemy>=2.0.0
Provides-Extra: dev
Requires-Dist: black>=23.0.0; extra == "dev"
Requires-Dist: ruff>=0.1.0; extra == "dev"
Requires-Dist: build>=1.0.0; extra == "dev"
